{
  "annotations": {
    "list": [
      {
        "builtIn": 1,
        "datasource": {
          "type": "grafana",
          "uid": "-- Grafana --"
        },
        "enable": true,
        "hide": true,
        "iconColor": "rgba(0, 211, 255, 1)",
        "name": "Annotations & Alerts",
        "type": "dashboard"
      }
    ]
  },
  "editable": true,
  "fiscalYearStartMonth": 0,
  "graphTooltip": 0,
  "id": 32,
  "links": [],
  "panels": [
    {
      "datasource": {
        "type": "loki",
        "uid": "cew2163rqp91cd"
      },
      "fieldConfig": {
        "defaults": {},
        "overrides": []
      },
      "gridPos": {
        "h": 8,
        "w": 24,
        "x": 0,
        "y": 0
      },
      "id": 1,
      "options": {
        "dedupStrategy": "none",
        "enableInfiniteScrolling": false,
        "enableLogDetails": true,
        "prettifyLogMessage": false,
        "showCommonLabels": false,
        "showLabels": false,
        "showTime": false,
        "sortOrder": "Descending",
        "wrapLogMessage": false
      },
      "pluginVersion": "12.1.0",
      "targets": [
        {
          "datasource": {
            "type": "loki",
            "uid": "cew2163rqp91cd"
          },
          "direction": "backward",
          "editorMode": "builder",
          "expr": "{container=\"user-service\"} |= ``",
          "queryType": "range",
          "refId": "A"
        }
      ],
      "title": "User Service Logs",
      "type": "logs"
    },
    {
      "datasource": {
        "type": "loki",
        "uid": "cew2163rqp91cd"
      },
      "fieldConfig": {
        "defaults": {},
        "overrides": []
      },
      "gridPos": {
        "h": 8,
        "w": 24,
        "x": 0,
        "y": 8
      },
      "id": 2,
      "options": {
        "dedupStrategy": "none",
        "enableInfiniteScrolling": false,
        "enableLogDetails": true,
        "prettifyLogMessage": false,
        "showCommonLabels": false,
        "showLabels": false,
        "showTime": false,
        "sortOrder": "Descending",
        "wrapLogMessage": false
      },
      "pluginVersion": "12.1.0",
      "targets": [
        {
          "datasource": {
            "type": "loki",
            "uid": "cew2163rqp91cd"
          },
          "direction": "backward",
          "editorMode": "builder",
          "expr": "{container=\"product-query-service\"} |= ``",
          "queryType": "range",
          "refId": "A"
        }
      ],
      "title": "Product Query Service Logs",
      "type": "logs"
    },
    {
      "datasource": {
        "type": "loki",
        "uid": "cew2163rqp91cd"
      },
      "fieldConfig": {
        "defaults": {},
        "overrides": []
      },
      "gridPos": {
        "h": 9,
        "w": 24,
        "x": 0,
        "y": 16
      },
      "id": 3,
      "options": {
        "dedupStrategy": "none",
        "enableInfiniteScrolling": false,
        "enableLogDetails": true,
        "prettifyLogMessage": false,
        "showCommonLabels": false,
        "showLabels": false,
        "showTime": false,
        "sortOrder": "Descending",
        "wrapLogMessage": false
      },
      "pluginVersion": "12.1.0",
      "targets": [
        {
          "datasource": {
            "type": "loki",
            "uid": "cew2163rqp91cd"
          },
          "direction": "backward",
          "editorMode": "builder",
          "expr": "{container=\"product-command-service\"} |= ``",
          "queryType": "range",
          "refId": "A"
        }
      ],
      "title": "Product Command Service Logs",
      "type": "logs"
    },
    {
      "datasource": {
        "type": "loki",
        "uid": "cew2163rqp91cd"
      },
      "fieldConfig": {
        "defaults": {},
        "overrides": []
      },
      "gridPos": {
        "h": 9,
        "w": 24,
        "x": 0,
        "y": 25
      },
      "id": 4,
      "options": {
        "dedupStrategy": "none",
        "enableInfiniteScrolling": false,
        "enableLogDetails": true,
        "prettifyLogMessage": false,
        "showCommonLabels": false,
        "showLabels": false,
        "showTime": false,
        "sortOrder": "Descending",
        "wrapLogMessage": false
      },
      "pluginVersion": "12.1.0",
      "targets": [
        {
          "datasource": {
            "type": "loki",
            "uid": "cew2163rqp91cd"
          },
          "direction": "backward",
          "editorMode": "builder",
          "expr": "{container=\"order-service\"} |= ``",
          "queryType": "range",
          "refId": "A"
        }
      ],
      "title": "Order Service Logs",
      "type": "logs"
    }
  ],
  "preload": false,
  "schemaVersion": 41,
  "tags": [],
  "templating": {
    "list": []
  },
  "time": {
    "from": "now-6h",
    "to": "now"
  },
  "timepicker": {},
  "timezone": "browser",
  "title": "POS Microservices - Logs",
  "uid": "dec9b557-c50d-417d-bc3c-1075de68cad0",
  "version": 10
}